pyfunc_logger/__init__.py
pyfunc_logger/logger.py
pyfunc_logger-1.0.0.dist-info/LICENSE
pyfunc_logger-1.0.0.dist-info/METADATA
pyfunc_logger-1.0.0.dist-info/WHEEL
pyfunc_logger-1.0.0.dist-info/top_level.txt
pyfunc_logger-1.0.0.dist-info/RECORD
