Metadata-Version: 2.2
Name: pyfunc_logger
Version: 1.0.0
Summary: Function call logging with precise timing for Python
Home-page: https://github.com/Yigal/pyfunc-logger
Author: Yigal Weinberger
Author-email: yigal.weinberger@gmail.com
Keywords: logging,debugging,profiling,performance,function-calls
Classifier: Programming Language :: Python :: 3
Classifier: License :: OSI Approved :: MIT License
Classifier: Operating System :: OS Independent
Classifier: Topic :: Software Development :: Debuggers
Classifier: Topic :: Software Development :: Libraries :: Python Modules
Classifier: Intended Audience :: Developers
Requires-Python: >=3.6
License-File: LICENSE
Dynamic: author
Dynamic: author-email
Dynamic: classifier
Dynamic: description
Dynamic: description-content-type
Dynamic: home-page
Dynamic: keywords
Dynamic: requires-python
Dynamic: summary
